{
  "brokerList": [
    "vs-test-ds.redfintest.com:9092"
  ],
  "whiteListTopics":[
    "^dev\.listing.*"
  ],
  "blackListTopics":[
    "__consumer_offsets",
    "localStateChangeLog",
    "__samza"
  ],
  "canaryTestTopics":[
    "kafka.canary.test"
  ],
  "replicationFactor": 3,
  "soTimeout": 100000,
  "bufferSize": 65536,
  "clientId": "test",
  "zooKeeperHosts": "test-zookeeper-1.redfintest.com:2181,test-zookeeper-2.redfintest.com:2181,test-zookeeper-3.redfintest.com:2181",
  "useZooKeeper": true,
  "acceptable_exception_count":5
}